pydoftools/__init__.py
pydoftools/npk/__init__.py
pydoftools/npk/consts.py
pydoftools/npk/extractor.py
pydoftools/npk/file.py
pydoftools/npk/npk.py
pydoftools/npk/img/__init__.py
pydoftools/npk/img/image/__init__.py
pydoftools/npk/img/image/color_board.py
pydoftools/npk/img/image/exception.py
pydoftools/npk/img/image/factory.py
pydoftools/npk/img/image/image.py
pydoftools/npk/img/image/link.py
pydoftools/npk/img/image/sprite.py
pydoftools/npk/img/image/extra/__init__.py
pydoftools/npk/img/image/extra/sprite.py
pydoftools/npk/img/image/extra/zlib.py
pydoftools/npk/img/image/format/__init__.py
pydoftools/npk/img/image/format/color.py
pydoftools/npk/img/image/format/convertor.py
pydoftools/npk/img/image/format/f1555.py
pydoftools/npk/img/image/format/f4444.py
pydoftools/npk/img/image/format/f8888.py
pydoftools/npk/img/image/format/factory.py
pydoftools/npk/img/image/format/format.py
pydoftools/npk/img/version/__init__.py
pydoftools/npk/img/version/factory.py
pydoftools/npk/img/version/img.py
pydoftools/npk/img/version/v1.py
pydoftools/npk/img/version/v2.py
pydoftools/npk/img/version/v4.py
pydoftools/npk/img/version/v5.py
pydoftools/npk/img/version/v6.py
pydoftools/pvf/__init__.py
pydoftools/pvf/enums.py
pydoftools/pvf/file_tree.py
pydoftools/pvf/formatter.py
pydoftools/pvf/header.py
pydoftools/pvf/parser.py
pydoftools/pvf/reader.py
pydoftools/pvf/utils.py
pydoftools/utils/__init__.py
pydoftools/utils/image.py
pydoftools/utils/io.py
pydoftools/utils/zlib.py
pydoftools-0.0.2.dist-info/LICENSE
pydoftools-0.0.2.dist-info/METADATA
pydoftools-0.0.2.dist-info/WHEEL
pydoftools-0.0.2.dist-info/top_level.txt
pydoftools-0.0.2.dist-info/RECORD
