Metadata-Version: 2.1
Name: pydoftools
Version: 0.0.2
Summary: A python library for dof-taiwan
Author-email: zhyipeng <zhyipeng@outlook.com>
Classifier: Programming Language :: Python :: 3
Classifier: Operating System :: OS Independent
Requires-Python: >=3.10
License-File: LICENSE
Requires-Dist: anyio >=3.6.2
Requires-Dist: loguru >=0.7.0
Requires-Dist: Pillow >=9.5.0
Requires-Dist: zhconv >=1.4.3
Provides-Extra: tqdm
Requires-Dist: tqdm ; extra == 'tqdm'
